asmc_data_module.cpython-36m-darwin.so
asmc_data_module-0.0.1.dist-info/COPYING
asmc_data_module-0.0.1.dist-info/LICENSE
asmc_data_module-0.0.1.dist-info/METADATA
asmc_data_module-0.0.1.dist-info/WHEEL
asmc_data_module-0.0.1.dist-info/top_level.txt
asmc_data_module-0.0.1.dist-info/RECORD
